pyright_cov.py
pyright_cov-0.2.2.dist-info/licenses/LICENSE.md
pyright_cov-0.2.2.dist-info/METADATA
pyright_cov-0.2.2.dist-info/WHEEL
pyright_cov-0.2.2.dist-info/entry_points.txt
pyright_cov-0.2.2.dist-info/top_level.txt
pyright_cov-0.2.2.dist-info/RECORD
