Metadata-Version: 2.4
Name: pyright-cov
Version: 0.2.2
Summary: Run Pyright and enforce minimum type coverage
Requires-Python: >=3.9
License-File: LICENSE.md
Requires-Dist: pyright
Dynamic: license-file
